{"nodes": [{"id": "bot_telegrampeer", "label": "TelegramPeer", "file_type": "code", "source_file": "repowire/telegram/bot.py", "source_location": null, "source_url": null, "captured_at": null, "author": null, "contributor": null}, {"id": "bot_pendingretry", "label": "PendingRetry", "file_type": "code", "source_file": "repowire/telegram/bot.py", "source_location": null, "source_url": null, "captured_at": null, "author": null, "contributor": null}, {"id": "bot_compute_visible_recents", "label": "compute_visible_recents", "file_type": "code", "source_file": "repowire/telegram/bot.py", "source_location": null, "source_url": null, "captured_at": null, "author": null, "contributor": null}, {"id": "bot_build_reply_keyboard", "label": "build_reply_keyboard", "file_type": "code", "source_file": "repowire/telegram/bot.py", "source_location": null, "source_url": null, "captured_at": null, "author": null, "contributor": null}, {"id": "bot_parse_keyboard_tap", "label": "parse_keyboard_tap", "file_type": "code", "source_file": "repowire/telegram/bot.py", "source_location": null, "source_url": null, "captured_at": null, "author": null, "contributor": null}, {"id": "bot_ws_loop", "label": "TelegramPeer._ws_loop", "file_type": "code", "source_file": "repowire/telegram/bot.py", "source_location": null, "source_url": null, "captured_at": null, "author": null, "contributor": null}, {"id": "bot_poll_loop", "label": "TelegramPeer._poll_loop", "file_type": "code", "source_file": "repowire/telegram/bot.py", "source_location": null, "source_url": null, "captured_at": null, "author": null, "contributor": null}, {"id": "bot_on_text", "label": "TelegramPeer._on_text", "file_type": "code", "source_file": "repowire/telegram/bot.py", "source_location": null, "source_url": null, "captured_at": null, "author": null, "contributor": null}, {"id": "bot_on_photo", "label": "TelegramPeer._on_photo", "file_type": "code", "source_file": "repowire/telegram/bot.py", "source_location": null, "source_url": null, "captured_at": null, "author": null, "contributor": null}, {"id": "bot_select_peer", "label": "TelegramPeer._select_peer", "file_type": "code", "source_file": "repowire/telegram/bot.py", "source_location": null, "source_url": null, "captured_at": null, "author": null, "contributor": null}, {"id": "bot_notify", "label": "TelegramPeer._notify", "file_type": "code", "source_file": "repowire/telegram/bot.py", "source_location": null, "source_url": null, "captured_at": null, "author": null, "contributor": null}, {"id": "bot_current_reply_keyboard", "label": "TelegramPeer._current_reply_keyboard", "file_type": "code", "source_file": "repowire/telegram/bot.py", "source_location": null, "source_url": null, "captured_at": null, "author": null, "contributor": null}, {"id": "bot_fetch_online_peers", "label": "TelegramPeer._fetch_online_peers", "file_type": "code", "source_file": "repowire/telegram/bot.py", "source_location": null, "source_url": null, "captured_at": null, "author": null, "contributor": null}, {"id": "bot_cmd_peers", "label": "TelegramPeer._cmd_peers", "file_type": "code", "source_file": "repowire/telegram/bot.py", "source_location": null, "source_url": null, "captured_at": null, "author": null, "contributor": null}, {"id": "bot_main", "label": "telegram bot main entrypoint", "file_type": "code", "source_file": "repowire/telegram/bot.py", "source_location": null, "source_url": null, "captured_at": null, "author": null, "contributor": null}, {"id": "bot_sticky_routing", "label": "Sticky Reply-Target Routing", "file_type": "code", "source_file": "repowire/telegram/bot.py", "source_location": null, "source_url": null, "captured_at": null, "author": null, "contributor": null}, {"id": "bot_attachments_flow", "label": "Telegram Photo Attachment Upload Flow", "file_type": "code", "source_file": "repowire/telegram/bot.py", "source_location": null, "source_url": null, "captured_at": null, "author": null, "contributor": null}], "edges": [{"source": "bot_build_reply_keyboard", "target": "bot_compute_visible_recents", "relation": "calls", "confidence": "EXTRACTED", "confidence_score": 1.0, "source_file": "repowire/telegram/bot.py", "source_location": null, "weight": 1.0}, {"source": "bot_current_reply_keyboard", "target": "bot_build_reply_keyboard", "relation": "calls", "confidence": "EXTRACTED", "confidence_score": 1.0, "source_file": "repowire/telegram/bot.py", "source_location": null, "weight": 1.0}, {"source": "bot_current_reply_keyboard", "target": "bot_fetch_online_peers", "relation": "calls", "confidence": "EXTRACTED", "confidence_score": 1.0, "source_file": "repowire/telegram/bot.py", "source_location": null, "weight": 1.0}, {"source": "bot_on_text", "target": "bot_parse_keyboard_tap", "relation": "calls", "confidence": "EXTRACTED", "confidence_score": 1.0, "source_file": "repowire/telegram/bot.py", "source_location": null, "weight": 1.0}, {"source": "bot_on_text", "target": "bot_select_peer", "relation": "calls", "confidence": "EXTRACTED", "confidence_score": 1.0, "source_file": "repowire/telegram/bot.py", "source_location": null, "weight": 1.0}, {"source": "bot_on_text", "target": "bot_notify", "relation": "calls", "confidence": "EXTRACTED", "confidence_score": 1.0, "source_file": "repowire/telegram/bot.py", "source_location": null, "weight": 1.0}, {"source": "bot_on_text", "target": "bot_cmd_peers", "relation": "calls", "confidence": "EXTRACTED", "confidence_score": 1.0, "source_file": "repowire/telegram/bot.py", "source_location": null, "weight": 1.0}, {"source": "bot_on_photo", "target": "bot_notify", "relation": "calls", "confidence": "EXTRACTED", "confidence_score": 1.0, "source_file": "repowire/telegram/bot.py", "source_location": null, "weight": 1.0}, {"source": "bot_select_peer", "target": "bot_notify", "relation": "calls", "confidence": "EXTRACTED", "confidence_score": 1.0, "source_file": "repowire/telegram/bot.py", "source_location": null, "weight": 1.0}, {"source": "bot_select_peer", "target": "bot_pendingretry", "relation": "references", "confidence": "EXTRACTED", "confidence_score": 1.0, "source_file": "repowire/telegram/bot.py", "source_location": null, "weight": 1.0}, {"source": "bot_notify", "target": "bot_pendingretry", "relation": "references", "confidence": "EXTRACTED", "confidence_score": 1.0, "source_file": "repowire/telegram/bot.py", "source_location": null, "weight": 1.0}, {"source": "bot_main", "target": "bot_telegrampeer", "relation": "references", "confidence": "EXTRACTED", "confidence_score": 1.0, "source_file": "repowire/telegram/bot.py", "source_location": null, "weight": 1.0}, {"source": "bot_telegrampeer", "target": "bot_ws_loop", "relation": "calls", "confidence": "EXTRACTED", "confidence_score": 1.0, "source_file": "repowire/telegram/bot.py", "source_location": null, "weight": 1.0}, {"source": "bot_telegrampeer", "target": "bot_poll_loop", "relation": "calls", "confidence": "EXTRACTED", "confidence_score": 1.0, "source_file": "repowire/telegram/bot.py", "source_location": null, "weight": 1.0}, {"source": "bot_on_photo", "target": "claudemd_attachments", "relation": "implements", "confidence": "INFERRED", "confidence_score": 0.85, "source_file": "repowire/telegram/bot.py", "source_location": null, "weight": 1.0}, {"source": "bot_attachments_flow", "target": "bot_on_photo", "relation": "references", "confidence": "EXTRACTED", "confidence_score": 1.0, "source_file": "repowire/telegram/bot.py", "source_location": null, "weight": 1.0}, {"source": "bot_sticky_routing", "target": "bot_on_text", "relation": "references", "confidence": "EXTRACTED", "confidence_score": 1.0, "source_file": "repowire/telegram/bot.py", "source_location": null, "weight": 1.0}, {"source": "bot_sticky_routing", "target": "bot_select_peer", "relation": "references", "confidence": "EXTRACTED", "confidence_score": 1.0, "source_file": "repowire/telegram/bot.py", "source_location": null, "weight": 1.0}, {"source": "bot_pendingretry", "target": "bot_select_peer", "relation": "shares_data_with", "confidence": "EXTRACTED", "confidence_score": 1.0, "source_file": "repowire/telegram/bot.py", "source_location": null, "weight": 1.0}, {"source": "bot_pendingretry", "target": "bot_notify", "relation": "shares_data_with", "confidence": "EXTRACTED", "confidence_score": 1.0, "source_file": "repowire/telegram/bot.py", "source_location": null, "weight": 1.0}], "hyperedges": [{"id": "telegram_keyboard_pipeline", "label": "Telegram Reply-Keyboard Pipeline", "nodes": ["bot_compute_visible_recents", "bot_build_reply_keyboard", "bot_parse_keyboard_tap", "bot_current_reply_keyboard", "bot_on_text"], "relation": "participate_in", "confidence": "EXTRACTED", "confidence_score": 0.9, "source_file": "repowire/telegram/bot.py"}]}